fastcons.cpython-312-x86_64-linux-musl.so
fastcons-0.5.0.dist-info/top_level.txt
fastcons-0.5.0.dist-info/RECORD
fastcons-0.5.0.dist-info/LICENSE.txt
fastcons-0.5.0.dist-info/METADATA
fastcons-0.5.0.dist-info/WHEEL
