Metadata-Version: 2.1
Name: fastcons
Version: 0.5.0
Summary: A cons extension module for Python
Author-email: Joshua Munn <public@elysee-munn.family>
Classifier: Development Status :: 3 - Alpha
Classifier: License :: OSI Approved :: MIT License
Classifier: Programming Language :: Python
Classifier: Programming Language :: Python :: 3
Classifier: Programming Language :: Python :: 3.12
Classifier: Programming Language :: Python :: 3.13
Requires-Python: <3.14,>=3.12
License-File: LICENSE.txt
Provides-Extra: build
Requires-Dist: build ==0.10.0 ; extra == 'build'
Provides-Extra: dev
Requires-Dist: ruff ==0.7.2 ; extra == 'dev'
Requires-Dist: pyright ==1.1.386 ; extra == 'dev'
Provides-Extra: test
Requires-Dist: pytest ==7.2.2 ; extra == 'test'
Requires-Dist: hypothesis <7,>=6 ; extra == 'test'
